setup.py
django_xforwardedfor_middleware.egg-info/PKG-INFO
django_xforwardedfor_middleware.egg-info/SOURCES.txt
django_xforwardedfor_middleware.egg-info/dependency_links.txt
django_xforwardedfor_middleware.egg-info/top_level.txt
x_forwarded_for/__init__.py
x_forwarded_for/middleware.py