Metadata-Version: 1.1
Name: django-xforwardedfor-middleware
Version: 1.0
Summary: Django X-Forwarded-For Middleware
Home-page: https://github.com/allo-/django-xforwardedfor-middleware
Author: Alexander Schier
Author-email: allo@laxu.de
License: UNKNOWN
Platform: UNKNOWN
Classifier: Framework :: Django
Classifier: License :: Public Domain
Classifier: Operating System :: OS Independent
Classifier: Programming Language :: Python
